README.md
pyproject.toml
picteus_extension_sdk/__init__.py
picteus_extension_sdk/picteus_extension.py
picteus_extension_sdk.egg-info/PKG-INFO
picteus_extension_sdk.egg-info/SOURCES.txt
picteus_extension_sdk.egg-info/dependency_links.txt
picteus_extension_sdk.egg-info/requires.txt
picteus_extension_sdk.egg-info/top_level.txt
picteus_ws_client/__init__.py
picteus_ws_client/api_client.py
picteus_ws_client/api_response.py
picteus_ws_client/configuration.py
picteus_ws_client/exceptions.py
picteus_ws_client/py.typed
picteus_ws_client/rest.py
picteus_ws_client/api/__init__.py
picteus_ws_client/api/administration_api.py
picteus_ws_client/api/api_secret_api.py
picteus_ws_client/api/extension_api.py
picteus_ws_client/api/image_api.py
picteus_ws_client/api/image_attachment_api.py
picteus_ws_client/api/miscellaneous_api.py
picteus_ws_client/api/repository_api.py
picteus_ws_client/api/settings_api.py
picteus_ws_client/models/__init__.py
picteus_ws_client/models/api_secret.py
picteus_ws_client/models/api_secret_summary.py
picteus_ws_client/models/api_secret_type.py
picteus_ws_client/models/application_metadata.py
picteus_ws_client/models/application_metadata_item.py
picteus_ws_client/models/application_metadata_item_value.py
picteus_ws_client/models/command_entity.py
picteus_ws_client/models/computed_image_format.py
picteus_ws_client/models/configuration_capability.py
picteus_ws_client/models/configuration_extension_command.py
picteus_ws_client/models/dates.py
picteus_ws_client/models/extension.py
picteus_ws_client/models/extension_activity.py
picteus_ws_client/models/extension_activity_kind.py
picteus_ws_client/models/extension_and_manual.py
picteus_ws_client/models/extension_generation_options.py
picteus_ws_client/models/extension_image_embeddings.py
picteus_ws_client/models/extension_image_feature.py
picteus_ws_client/models/extension_image_tag.py
picteus_ws_client/models/extension_manual.py
picteus_ws_client/models/extension_settings.py
picteus_ws_client/models/extension_status.py
picteus_ws_client/models/extensions_configuration.py
picteus_ws_client/models/generation_recipe.py
picteus_ws_client/models/generation_recipe_prompt.py
picteus_ws_client/models/image.py
