Metadata-Version: 2.4
Name: picteus-extension-sdk
Version: 0.8.0
Summary: The Picteus extension Python SDK.
Author: picteus-extension-sdk
Project-URL: Homepage, https://github.com/picteus/Picteus
Project-URL: Repository, https://github.com/picteus/Picteus
Keywords: Picteus,extension,SDK
Classifier: Development Status :: 4 - Beta
Classifier: Intended Audience :: Developers
Classifier: Programming Language :: Python :: 3.11
Requires-Python: >=3.8
Requires-Dist: python_dateutil>=2.8.2
Requires-Dist: urllib3<3.0.0,>=2.1.0
Requires-Dist: pydantic>=2
Requires-Dist: typing-extensions>=4.7.1
Requires-Dist: python-socketio[asyncio_client]==5.16.0
Requires-Dist: aiohttp==3.13.2
Requires-Dist: requests==2.32.5
